miniflare/__init__.py
miniflare/cloudflare_api.py
miniflare/config.py
miniflare/extension.py
localstack_extension_miniflare-0.1.3.dist-info/LICENSE
localstack_extension_miniflare-0.1.3.dist-info/METADATA
localstack_extension_miniflare-0.1.3.dist-info/WHEEL
localstack_extension_miniflare-0.1.3.dist-info/entry_points.txt
localstack_extension_miniflare-0.1.3.dist-info/top_level.txt
localstack_extension_miniflare-0.1.3.dist-info/RECORD
