Metadata-Version: 2.1
Name: localstack-extension-miniflare
Version: 0.1.3
Summary: LocalStack Extension: Miniflare
Home-page: https://github.com/localstack/localstack-extensions/tree/main/miniflare
Author: Waldemar Hummer
Author-email: waldemar@localstack.cloud
License-File: LICENSE
Provides-Extra: dev
Requires-Dist: localstack-core>=1.0.0; extra == "dev"
